newa_downloader/__init__.py
newa_downloader/coordinates.py
newa_downloader/core.py
newa_downloader/py.typed
newa_downloader/time_span.py
newa_downloader/mesoscale/__init__.py
newa_downloader/mesoscale/climate.py
newa_downloader/mesoscale/timeseries.py
newa_downloader/microscale/__init__.py
newa_downloader/microscale/climate.py
newa_downloader-0.0.2.dist-info/LICENSE
newa_downloader-0.0.2.dist-info/METADATA
newa_downloader-0.0.2.dist-info/WHEEL
newa_downloader-0.0.2.dist-info/top_level.txt
newa_downloader-0.0.2.dist-info/RECORD
