Metadata-Version: 2.1
Name: newa-downloader
Version: 0.0.2
Summary: A package to download data from the New European Wind Atlas
Author-email: Henry Korb <henry.korb@geo.uu.se>
Project-URL: Homepage, https://github.com/Hkorb/NEWA_downloader
Classifier: Programming Language :: Python :: 3
Classifier: License :: OSI Approved :: MIT License
Classifier: Operating System :: OS Independent
Requires-Python: >=3.7
License-File: LICENSE
Requires-Dist: requests
Provides-Extra: dev
Requires-Dist: pytest ; extra == 'dev'
Requires-Dist: ruff ; extra == 'dev'
